aivox/__init__.py
aivox/client.py
aivox-0.1.1.dist-info/METADATA
aivox-0.1.1.dist-info/WHEEL
aivox-0.1.1.dist-info/top_level.txt
aivox-0.1.1.dist-info/RECORD
