Metadata-Version: 2.1
Name: aivox
Version: 0.1.1
Summary: A simple API client for AI-Music Generate
Home-page: https://github.com/cropsun/aivox
Author: Cropsun
Author-email: martinsunshinesh@gmail.com
License: UNKNOWN
Platform: UNKNOWN
Classifier: Programming Language :: Python :: 3
Classifier: License :: OSI Approved :: MIT License
Classifier: Operating System :: OS Independent
Requires-Dist: requests
